mcp_server_coindesk/__init__.py
mcp_server_coindesk/page.py
mcp_server_coindesk/py.typed
mcp_server_coindesk/server.py
mcp_server_coindesk/utils.py
mcp_server_coindesk-0.1.0.dist-info/METADATA
mcp_server_coindesk-0.1.0.dist-info/WHEEL
mcp_server_coindesk-0.1.0.dist-info/entry_points.txt
mcp_server_coindesk-0.1.0.dist-info/licenses/LICENSE
mcp_server_coindesk-0.1.0.dist-info/RECORD
